motorodm/__init__.py
motorodm/documents/__init__.py
motorodm/documents/document.py
motorodm/documents/document_iterator.py
motorodm/documents/document_mixin.py
motorodm/documents/embedded_document.py
motorodm/documents/meta_document.py
motorodm/fields/__init__.py
motorodm/fields/boolean_field.py
motorodm/fields/datetime_field.py
motorodm/fields/decimal_field.py
motorodm/fields/embedded_document_field.py
motorodm/fields/field.py
motorodm/fields/float_field.py
motorodm/fields/int_field.py
motorodm/fields/json_field.py
motorodm/fields/list_field.py
motorodm/fields/object_id_field.py
motorodm/fields/reference_field.py
motorodm/fields/string_field.py
motorodm/query_sets/__init__.py
motorodm/query_sets/class_query_set.py
motorodm/query_sets/instance_query_set.py
motorodm/query_sets/query_set.py
motorodm/utils/__init__.py
motorodm/utils/types.py
motorodm-0.0.10.dist-info/LICENSE
motorodm-0.0.10.dist-info/METADATA
motorodm-0.0.10.dist-info/WHEEL
motorodm-0.0.10.dist-info/top_level.txt
motorodm-0.0.10.dist-info/RECORD
